{
  "routes": [
    {
      "method": "GET",
      "path": "/upcs",
      "handler": "upc.find",
      "config": {
        "policies": []
      }
    },
    {
      "method": "GET",
      "path": "/upcs/count",
      "handler": "upc.count",
      "config": {
        "policies": []
      }
    },
    {
      "method": "GET",
      "path": "/upcs/:id",
      "handler": "upc.findOne",
      "config": {
        "policies": []
      }
    },
    {
      "method": "POST",
      "path": "/upcs",
      "handler": "upc.create",
      "config": {
        "policies": []
      }
    },
    {
      "method": "PUT",
      "path": "/upcs/:id",
      "handler": "upc.update",
      "config": {
        "policies": []
      }
    },
    {
      "method": "DELETE",
      "path": "/upcs/:id",
      "handler": "upc.delete",
      "config": {
        "policies": []
      }
    }
  ]
}
